README.md
requirements.txt
setup.py
web_frame/__init__.py
web_frame/context.py
web_frame/router.py
web_frame/server.py
web_frame.egg-info/PKG-INFO
web_frame.egg-info/SOURCES.txt
web_frame.egg-info/dependency_links.txt
web_frame.egg-info/requires.txt
web_frame.egg-info/top_level.txt
web_frame/frame/BaseHandler.py
web_frame/frame/DocHandler.py
web_frame/frame/HandlerHelper.py
web_frame/frame/__init__.py
web_frame/templates/doc.html
web_frame/templates/record.html
web_frame/utils/CacheUtil.py
web_frame/utils/CommonUtil.py
web_frame/utils/DBUtil.py
web_frame/utils/DataClient.py
web_frame/utils/FileUtil.py
web_frame/utils/JwtUtil.py
web_frame/utils/MongodbUtil.py
web_frame/utils/MysqlUtil.py
web_frame/utils/RSAUtil.py
web_frame/utils/SqlFormatUtil.py
web_frame/utils/__init__.py